{
  "pig": [
    "Piglets joyfully snort and play in the lively farmyard.",
    "Cheerful piggy antics continue with playful oinks and snorts.",
    "Sunny farm vibes as pigs chatter in delightful conversations.",
    "Curious piglets exploring with joyful grunts and snorts."
  ],
  "thunderstorm": [
    "Nature's drama unfolds with roaring thunder and torrential rain.",
    "Stormy symphony: thunder echoes, rain drums, and wind howls.",
    "Dramatic thunderstorm intensifies with booming thunder and heavy rain.",
    "Electrifying storm ambiance with powerful thunder and relentless rain."
  ],
  "coughing": [
    "Persistent coughing persists, signaling discomfort or illness.",
    "Coughing symphony: a variety of coughs express different conditions.",
    "A series of coughs echo, each telling a unique health story.",
    "Coughs of varying intensity, revealing different health discomforts."
  ],
  "brushing_teeth": [
    "Morning ritual: toothbrush hums in the diligent care of teeth.",
    "The rhythmic dance of bristles as teeth receive meticulous cleaning.",
    "Dental harmony: the buzzing toothbrush creates a refreshing ambiance.",
    "Precision in oral care: the whir of a diligent toothbrush in action."
  ],
  "crying_baby": [
    "Tender cries and gentle whimpers create an emotional soundscape.",
    "Expressive sobs and baby cries tell tales of needs and comfort.",
    "Emotional crescendo as a baby communicates through heartfelt cries.",
    "Babbling baby soundtrack: cries, whimpers, and coos intertwine."
  ],
  "vacuum_cleaner": [
    "Diligent vacuum tackles dust and debris with a purposeful hum.",
    "Efficient cleaning mission unfolds with the persistent vacuum soundtrack.",
    "The sweeping soundscape of a vacuum cleaning every nook and cranny.",
    "A clean sweep: the vacuum hums as it works its cleaning magic."
  ],
  "hen": [
    "Clucking hens create a lively barnyard opera of chirps and squawks.",
    "Bustling hen activity unfolds with clucks, squabbles, and pecks.",
    "The daily gossip session: hens clucking and sharing barnyard tales.",
    "Feathered conversations continue with clucks, squawks, and pecks."
  ],
  "insects": [
    "Nature's orchestra features buzzing insects in a vibrant performance.",
    "A buzzworthy concert: insects harmonize in the rhythm of nature.",
    "Insect ensemble creates a lively soundscape in the great outdoors.",
    "Outdoor symphony: insects contribute to the vibrant sounds of nature."
  ],
  "dog": [
    "Canine choir expresses joy, excitement, and playful camaraderie.",
    "Barks, whines, and tail wags form a symphony of canine communication.",
    "The diverse language of dogs unfolds in a dynamic vocal tapestry.",
    "Four-legged communication continues with barks, growls, and whimpers."
  ],
  "clock_alarm": [
    "Intrusive alarm insists on attention, a persistent wake-up call.",
    "Morning urgency: clock alarm demands action with determined ringing.",
    "Alarm urgency rises as the insistent clock disrupts the silence.",
    "Ringing wake-up call: the insistent alarm demands immediate attention."
  ],
  "frog": [
    "Froggy serenade continues with melodic croaks in the moonlight.",
    "Peaceful pond ambiance painted by the rhythmic croaking of frogs.",
    "Frogs collaborate to create a tranquil symphony of croaks.",
    "Moonlit serenade: frogs croak in harmony under the night sky."
  ],
  "breathing": [
    "Calm breathing rhythms create an oasis of tranquility.",
    "Deep breaths echo serenity, capturing a moment of calm.",
    "Relaxation unfolds in the measured cadence of rhythmic breathing.",
    "Mindful breathing: the rhythmic inhale and exhale of a calm moment."
  ],
  "mouse_click": [
    "Swift and precise clicks resonate as a mouse navigates effortlessly.",
    "Keyboard dance: the rhythmic clicking of a mouse in action.",
    "Digital melody unfolds with the symphony of mouse clicks.",
    "The dance of digits: a computer mouse orchestrates a rhythmic symphony."
  ],
  "cow": [
    "Contented moos create a peaceful pastoral soundscape.",
    "Mellow mooing continues as cows graze in the sunlit meadow.",
    "Cows contribute to a harmonious farm ambiance with gentle moos.",
    "The symphony of cows: gentle moos resonate in a tranquil meadow."
  ],
  "drinking_sipping": [
    "Satisfying sips and gulps compose a refreshing beverage melody.",
    "Quenching thirst with the musical accompaniment of sipping sounds.",
    "A symphony of hydration: each sip contributes to the liquid score.",
    "Refreshing beverage experience enhanced by the symphony of sips."
  ],
  "water_drops": [
    "Gentle droplets form a soothing percussion in the water symphony.",
    "Rhythmic water droplets create a tranquil and calming melody.",
    "Drip-drop serenity: the sound of water droplets orchestrating relaxation.",
    "A rain of tranquility: the rhythmic patter of water droplets in harmony."
  ],
  "sheep": [
    "Bleating sheep contribute to the serene soundscape of a meadow.",
    "Pastoral poetry: sheep bleats harmonize in a peaceful countryside.",
    "Grazing sheep add their musical bleats to the natural orchestra.",
    "Symphony of sheep: contented bleats echo in a serene pasture."
  ],
  "rooster": [
    "Proud rooster crows herald the dawn with energetic bravado.",
    "Morning proclamation: the confident crowing of a vigilant rooster.",
    "The farm wakes up to the lively sounds of a rooster's triumphant crows.",
    "Rooster serenade: dawn breaks with the proud crowing of a rooster."
  ],
  "crow": [
    "Cawing chorus of crows creates an atmospheric and mysterious aura.",
    "Mystical echoes unfold as crows communicate with haunting caws.",
    "Crows converse in a dark symphony of mysterious and expressive caws.",
    "Feathered mystique: crows create an enigmatic soundscape with their caws."
  ],
  "cat": [
    "Feline melodies: meows and purrs express a cat's varied emotions.",
    "Cat communication unfolds in a charming medley of meows and purrs.",
    "A tapestry of cat language woven with expressive meows and soothing purrs.",
    "Cats at play: meows, purrs, and playful chirps create a whimsical melody."
  ],
  "chirping_birds": [
    "Melodic chirps paint a harmonious soundscape in the heart of nature.",
    "Avian choir: birds chirp in a symphony, celebrating the dawn.",
    "Chirping birds compose a lively and joyful melody in the treetops.",
    "Feathered serenade: chirping birds create a lively woodland symphony."
  ],
  "sneezing": [
    "Sudden and spontaneous sneezes punctuate the audio canvas unpredictably.",
    "Unpredictable bursts: the distinctive sound of a spontaneous sneeze.",
    "A brief and involuntary burst as the body releases a sudden sneeze.",
    "Unexpected sneezes: the canvas is punctuated by sudden bursts of sound."
  ],
  "door_wood_knock": [
    "Distinctive knocks on a wooden door announce a visitor's arrival.",
    "The timeless sound of a wooden door being knocked with purpose.",
    "A visitor's presence signaled by the familiar knock on a wooden door.",
    "Wooden door ritual: knocks resonate, heralding the arrival of a guest."
  ],
  "can_opening": [
    "Crackling suspense builds as a can is opened with precision.",
    "Anticipation unfolds in the crackling sound of a can being opened.",
    "Revelation in a can: suspenseful moments captured in the opening sound.",
    "The unveiling: can opening creates a suspenseful and crackling ambiance."
  ],
  "crackling_fire": [
    "Cozy ambiance abounds with the warm crackling of a lively fire.",
    "Crackling fireplace serenades with warmth on a cold evening.",
    "The comforting symphony of a crackling fire, casting a warm glow.",
    "Fireplace crackles: warmth and comfort emanate from the lively flames."
  ],
  "glass_breaking": [
    "Tension erupts as sharp and resonant sounds shatter the silence.",
    "Dramatic moment captured in the sharp sound of glass breaking.",
    "A moment of impact as glass shatters into a cacophony of fragments.",
    "Breaking point: the tension builds and erupts in the shattering of glass."
  ],
  "clock_tick": [
    "Steady ticking marks the heartbeat of time in rhythmic precision.",
    "The reassuring cadence of a ticking clock, measuring moments.",
    "Time unfolds in the rhythmic heartbeat of the steady ticking clock.",
    "Clock symphony: rhythmic ticking resonates, measuring the passage of time."
  ],
  "washing_machine": [
    "Efficient sounds of a washing machine orchestrate a domestic choreography.",
    "Rhythmic hum of the washing machine as it tackles laundry tasks.",
    "Domestic harmony: the washing machine completes its tasks with precision.",
    "Laundry day melody: the washing machine hums in a rhythmic symphony."
  ],
  "laughing": [
    "Infectious laughter echoes, creating ripples of joy and shared happiness.",
    "Joyful laughter weaves a tapestry of shared happiness and amusement.",
    "The lively symphony of laughter, a celebration of shared moments.",
    "Laughter contagion: infectious joy echoes in the harmonious soundscape."
  ],
  "crickets": [
    "Nocturnal crickets serenade the night with their calming and rhythmic chirps.",
    "Nighttime lullaby: crickets contribute to a serene nocturnal soundscape.",
    "Moonlit serenade unfolds as crickets harmonize in the quiet of the night.",
    "Nocturnal symphony: crickets create a soothing melody under the moonlight."
  ],
  "clapping": [
    "Enthusiastic applause and rhythmic clapping express appreciation and acclaim.",
    "Applause unfolds in a rhythmic dance, acknowledging a performance.",
    "An energetic soundscape painted by the rhythmic clapping of an appreciative audience.",
    "Appreciation in rhythm: clapping hands resonate in an energetic applause."
  ],
  "pouring_water": [
    "Flowing water creates a liquid symphony, soothing and rhythmic.",
    "Calming cascade: the gentle sound of water pouring into a container.",
    "A refreshing moment accompanied by the rhythmic sounds of pouring water.",
    "Liquid melody: the soothing sounds of water create a refreshing ambiance."
  ],
  "sea_waves": [
    "Gentle and rhythmic sounds of ocean waves create a serene coastal ambiance.",
    "Seashore serenity: waves ebb and flow in a calming rhythmic dance.",
    "A tranquil soundscape painted by the soothing rhythm of sea waves.",
    "Oceanic harmony: the rhythmic dance of waves creates a soothing symphony."
  ],
  "door_wood_creaks": [
    "Eerie creaks resonate as a wooden door swings open or closed mysteriously.",
    "Suspenseful entrance: the distinctive creak of a wooden door in motion.",
    "A touch of mystery added by the eerie creaks of a swinging wooden door.",
    "Wooden door drama: creaks add an air of suspense to each motion."
  ],
  "rain": [
    "Soft and soothing rainfall creates a meditative and calming ambiance.",
    "Nature's lullaby: raindrops compose a gentle and rhythmic melody.",
    "A tranquil soundscape painted by the rhythmic and comforting sound of rain.",
    "Rainy day symphony: the patter of raindrops creates a soothing cadence."
  ],
  "toilet_flush": [
    "Efficient flushing sound marks the completion of a hygienic routine.",
    "The distinctive sound of a toilet flush concludes the cleansing process.",
    "Hygienic closure: the efficient sound of a toilet flushing after use.",
    "Toilet ritual: the flushing sound signifies the end of a routine."
  ],
  "wind": [
    "Howling wind gusts through the landscape, an untamed force of nature.",
    "Dynamic wind symphony: gusts create an elemental and powerful soundscape.",
    "A symphony of wind, capturing the majestic and untamed essence of nature.",
    "Whistling winds: nature's breath creates a powerful and atmospheric symphony."
  ],
  "snoring": [
    "Deep and rhythmic snores provide a comforting soundtrack of peaceful slumber.",
    "The rhythmic melody of snoring, evidence of restful and undisturbed sleep.",
    "A lullaby of sleep captured in the rhythmic and soothing sounds of snoring.",
    "Soothing snores: the sound of peaceful sleep echoes in the night."
  ],
  "keyboard_typing": [
    "Precise tapping and clicking of keys resonate in a focused and productive rhythm.",
    "The rhythmic sounds of keyboard typing form a symphony of productivity.",
    "Productive harmony: the efficient and deliberate sounds of keyboard typing.",
    "Keyboard cadence: the rhythmic dance of keys in a symphony of typing."
  ],
  "footsteps": [
    "Assorted footsteps narrate diverse stories through their distinctive sounds.",
    "The rhythmic dance of footsteps, each step telling a unique tale.",
    "A dynamic soundscape painted by the rhythm and diversity of footsteps.",
    "Footstep narrative: the varied sounds echo stories with each step taken."
  ]
}